LICENSE.txt
README.md
setup.cfg
setup.py
ftp_downloader/FTPDownloader.py
ftp_downloader/__init__.py
ftp_downloader.egg-info/PKG-INFO
ftp_downloader.egg-info/SOURCES.txt
ftp_downloader.egg-info/dependency_links.txt
ftp_downloader.egg-info/requires.txt
ftp_downloader.egg-info/top_level.txt