Metadata-Version: 2.1
Name: ftp-downloader
Version: 0.3
Summary: Simple async ftp downloader based on aioftp. Download only modified files.
Home-page: https://github.com/bigpe/FtpDownloader
Author: Aleksandr Sokolov
Author-email: bigpewm@gmail.com
License: MIT
Download-URL: https://github.com/bigpe/FtpDownloader/archive/pypi-0.3.tar.gz
Keywords: ftp,python3.7,asyncio ,aioftp,ftp-client,download,ftp
Platform: UNKNOWN
Classifier: Development Status :: 3 - Alpha
Classifier: Intended Audience :: Developers
Classifier: Topic :: Software Development :: Build Tools
Classifier: License :: OSI Approved :: MIT License
Classifier: Programming Language :: Python :: 3.7
Classifier: Programming Language :: Python :: 3.8
Classifier: Programming Language :: Python :: 3.9
